LICENSE
README.md
setup.py
deleterious/DeleteMultipleMixin.py
deleterious/__init__.py
drf_deleterious.egg-info/PKG-INFO
drf_deleterious.egg-info/SOURCES.txt
drf_deleterious.egg-info/dependency_links.txt
drf_deleterious.egg-info/top_level.txt