Metadata-Version: 2.1
Name: drf-deleterious
Version: 0.1.0
Summary: DRF Deleterious: A simple mixin package for Django REST Framework which adds Deleting Multiple requested entities in a single DELETE request
Home-page: https://github.com/Gautam-Diwan/drf-deleterious
Author: Gautam Diwan
Author-email: gautamdiwan3@email.com
License: MIT
Platform: UNKNOWN
Classifier: License :: OSI Approved :: MIT License
Classifier: Programming Language :: Python :: 3
Classifier: Programming Language :: Python :: 3.7
Classifier: Programming Language :: Python :: 3.8
Classifier: Programming Language :: Python :: 3.9
Requires-Python: >=3.6
License-File: LICENSE
